pyEX/studies/__init__.py
pyEX/studies/_version.py
pyEX/studies/peercorrelation.py
pyEX/studies/utils.py
pyEX.studies-0.1.0.dist-info/LICENSE
pyEX.studies-0.1.0.dist-info/METADATA
pyEX.studies-0.1.0.dist-info/WHEEL
pyEX.studies-0.1.0.dist-info/top_level.txt
pyEX.studies-0.1.0.dist-info/RECORD
