Metadata-Version: 2.1
Name: pyEX.studies
Version: 0.1.0
Summary: Rest API to IEX
Home-page: https://github.com/timkpaine/pyEX.studies
Author: Tim Paine
Author-email: t.paine154@gmail.com
License: Apache 2.0
Keywords: finance data
Platform: UNKNOWN
Classifier: Development Status :: 3 - Alpha
Classifier: Programming Language :: Python :: 3
Classifier: Programming Language :: Python :: 3.6
Classifier: Programming Language :: Python :: 3.7
Classifier: Programming Language :: Python :: 3.8
Requires-Dist: pandas (>=0.22.0)
Requires-Dist: pyEX (>=0.1.10)
Requires-Dist: TA-Lib (>=0.4.17)
Requires-Dist: temporal-cache (>=0.0.3)
Provides-Extra: dev
Requires-Dist: flake8 (>=3.7.8) ; extra == 'dev'
Requires-Dist: mock ; extra == 'dev'
Requires-Dist: pytest (>=4.3.0) ; extra == 'dev'
Requires-Dist: pytest-cov (>=2.6.1) ; extra == 'dev'
Requires-Dist: Sphinx (>=1.8.4) ; extra == 'dev'
Requires-Dist: sphinx-markdown-builder (>=0.5.2) ; extra == 'dev'
Requires-Dist: pandas (>=0.22.0) ; extra == 'dev'
Requires-Dist: pyEX (>=0.1.10) ; extra == 'dev'
Requires-Dist: TA-Lib (>=0.4.17) ; extra == 'dev'
Requires-Dist: temporal-cache (>=0.0.3) ; extra == 'dev'
